MANIFEST.in
setup.py
docs/HISTORY.txt
src/dolmen/__init__.py
src/dolmen.relations.egg-info/PKG-INFO
src/dolmen.relations.egg-info/SOURCES.txt
src/dolmen.relations.egg-info/dependency_links.txt
src/dolmen.relations.egg-info/namespace_packages.txt
src/dolmen.relations.egg-info/not-zip-safe
src/dolmen.relations.egg-info/requires.txt
src/dolmen.relations.egg-info/top_level.txt
src/dolmen/relations/README.txt
src/dolmen/relations/__init__.py
src/dolmen/relations/catalog.py
src/dolmen/relations/configure.zcml
src/dolmen/relations/container.py
src/dolmen/relations/events.py
src/dolmen/relations/ftesting.zcml
src/dolmen/relations/handlers.py
src/dolmen/relations/interfaces.py
src/dolmen/relations/tests.py
src/dolmen/relations/values.py
src/dolmen/relations/locales/fr/LC_MESSAGES/dolmen.relation.po